proofpoint_itm/__init__.py
proofpoint_itm/classes.py
proofpoint_itm/client.py
proofpoint_itm/models/identity.py
proofpoint_itm-0.10.0.dist-info/licenses/LICENSE
proofpoint_itm-0.10.0.dist-info/METADATA
proofpoint_itm-0.10.0.dist-info/WHEEL
proofpoint_itm-0.10.0.dist-info/top_level.txt
proofpoint_itm-0.10.0.dist-info/RECORD
