Metadata-Version: 2.4
Name: proofpoint_itm
Version: 0.10.0
Summary: Proofpoint ITM API client library
Author-email: Mike Olden <michael.olden@oldendigital.com>
License-Expression: Apache-2.0
Project-URL: Homepage, https://github.com/drizzo-tech/proofpoint_itm
Project-URL: Repository, https://github.com/drizzo-tech/proofpoint_itm
Project-URL: Documentation, https://proofpoint-itm.readthedocs.io/en/latest/index.html
Project-URL: Issues, https://github.com/drizzo-tech/proofpoint_itm/issues
Keywords: Proofpoint ITM,Proofpoint,ITM,ObserveIT
Classifier: Programming Language :: Python :: 3
Classifier: Operating System :: OS Independent
Requires-Python: >=3.8.1
License-File: LICENSE
Requires-Dist: requests
Requires-Dist: pydantic
Provides-Extra: build
Requires-Dist: setuptools; extra == "build"
Requires-Dist: wheel; extra == "build"
Provides-Extra: test
Requires-Dist: pytest>=7.4.0; extra == "test"
Requires-Dist: pytest-cov>=4.1.0; extra == "test"
Requires-Dist: pytest-mock>=3.11.1; extra == "test"
Requires-Dist: pytest-xdist>=3.3.0; extra == "test"
Requires-Dist: responses>=0.23.0; extra == "test"
Requires-Dist: python-dotenv>=1.0.0; extra == "test"
Provides-Extra: dev
Requires-Dist: pytest>=7.4.0; extra == "dev"
Requires-Dist: pytest-cov>=4.1.0; extra == "dev"
Requires-Dist: pytest-mock>=3.11.1; extra == "dev"
Requires-Dist: pytest-xdist>=3.3.0; extra == "dev"
Requires-Dist: responses>=0.23.0; extra == "dev"
Requires-Dist: python-dotenv>=1.0.0; extra == "dev"
Requires-Dist: flake8>=6.0.0; extra == "dev"
Requires-Dist: black>=23.0.0; extra == "dev"
Requires-Dist: mypy>=1.4.0; extra == "dev"
Dynamic: license-file
